[
  {
    "url": "https://www.youtube.com/shorts/w8lafxddWvw"
  },
  { 
    "url": "https://www.youtube.com/shorts/3_7kc-1b57A" 
  },
  {
    "url": "https://www.youtube.com/shorts/cLyfujDkB8A"
  },
  {
    "url": "https://www.youtube.com/shorts/EZZ56w2J0gs"
  },
  {
    "url": "https://www.youtube.com/shorts/ZJtaVBxpiP8"
  },
  {
    "url": "https://www.youtube.com/shorts/qzRVjin8KOs"
  },
  {
    "url": "https://www.youtube.com/shorts/vZVcNiu0an8"
  },
  {
    "url": "https://www.youtube.com/shorts/H0Fd788qFWU"
  },
  {
    "url": "https://www.youtube.com/shorts/lq8PJquIuMg"
  },
  {
    "url": "https://www.youtube.com/shorts/Hjly_IPSdoc"
  },
  {
    "url": "https://www.youtube.com/shorts/TPSCW4tOG54"
  },
  {
    "url": "https://www.youtube.com/shorts/_Fs0QgNif1E"
  },
  {
    "url": "https://www.youtube.com/shorts/gkP0URalfsQ"
  },
  {
    "url": "https://www.youtube.com/shorts/2U0eJvqVYMo"
  },
  {
    "url": "https://www.youtube.com/shorts/Wu4YktA1qbk"
  },
  {
    "url": "https://www.youtube.com/shorts/HIEuGP1KrA8"
  },
  {
    "url": "https://www.youtube.com/shorts/NebmBkDqOgo"
  },
  {
    "url": "https://www.youtube.com/shorts/WvYvN8Yifxc"
  },
  {
    "url": "https://www.youtube.com/watch?v=QwDLfOV8H_g"
  },
  {
    "url": "https://www.youtube.com/watch?v=xGHXKJYAEIE"
  },
  {
    "url": "https://www.youtube.com/watch?v=t0SUFfsU_gI"
  },
  {
    "url": "https://www.youtube.com/watch?v=9sJ-lkRh6UY"
  },
  {
    "url": "https://www.youtube.com/watch?v=1VuXe2qbj5U"
  },
  {
    "url": "https://www.youtube.com/watch?v=oLMnn1Pu6uQ"
  },
  {
    "url": "https://www.youtube.com/watch?v=F-uRuioOiDU"
  },
  {
    "url": "https://www.youtube.com/watch?v=aKU44aCesGo"
  }
]
